[
  {
    "ContainingType": "GiveNTake.Controllers.ProductsController",
    "Method": "GetProduct",
    "RelativePath": "api/Products",
    "HttpMethod": "",
    "IsController": true,
    "Order": 0,
    "Parameters": [],
    "ReturnTypes": [
      {
        "Type": "System.String[]",
        "MediaTypes": [
          "text/plain",
          "application/json",
          "text/json"
        ],
        "StatusCode": 200
      }
    ]
  },
  {
    "ContainingType": "GiveNTake.Controllers.ProductsController",
    "Method": "AddNewProduct",
    "RelativePath": "api/Products",
    "HttpMethod": "POST",
    "IsController": true,
    "Order": 0,
    "Parameters": [
      {
        "Name": "newProduct",
        "Type": "GiveNTake.Model.NewRequestDTO",
        "IsRequired": true
      }
    ],
    "ReturnTypes": [
      {
        "Type": "GiveNTake.Model.NewRequestDTO",
        "MediaTypes": [
          "text/plain",
          "application/json",
          "text/json"
        ],
        "StatusCode": 200
      }
    ]
  }
]